{
  "center_geohash": "9q4ybkmsmby0",
  "center_lat": 34.960603000000006,
  "center_lng": -119.864018,
  "description": "",
  "directions": "",
  "geohash": "9q4",
  "nearest_peak_geohash": "9q4wxfqjxurz",
  "photos": [],
  "source_url": "https://www.peakbagger.com/climber/ascent.aspx?aid=401688",
  "stats": {
    "Ascent Type": "Successful Summit Attained",
    "Date": "Sunday, March 30, 2014",
    "Elevation": "5606 ft / 1708 m",
    "Location": "USA-California",
    "Motorized Transport to Trailhead": "4x4 Vehicle",
    "Others in Party": "Larry Edmonds----Only Party on Mountain",
    "Peak": "Hot Benchmark",
    "Peakbagger.com": "\n\n\n",
    "Quality": "1 (on a subjective 1-10 scale)",
    "Round-Trip Distance": "0.4 mi / 0.6 km",
    "Route": "old firebreak",
    "Time": "6 Minutes",
    "Total Elevation Gain": "126 ft / 38 m",
    "Trailhead": "Sierra Madre Rd\u00a0\u00a05480 ft / 1670 m",
    "Weather": "Cool, Breezy, Overcast"
  },
  "title": "old firebreak",
  "trail_id": "pb_401688"
}