{
  "center_geohash": "drge4m5w22v5",
  "center_lat": 44.149637,
  "center_lng": -73.724424,
  "description": "",
  "directions": "",
  "geohash": "drge",
  "nearest_peak_geohash": "drge4y13f9uf",
  "photos": [],
  "source_url": "https://www.peakbagger.com/climber/ascent.aspx?aid=246497",
  "stats": {
    "Ascent Type": "Successful Summit Attained",
    "Date": "Sunday, June 10, 2012",
    "Elevation": "4390 ft / 1338 m",
    "Location": "USA-New York",
    "Others in Party": "Scott Duclos",
    "Peak": "Rocky Peak Ridge",
    "Peakbagger.com": "\n\n\n",
    "Route": "Zander Scott Trail (48) to Roaring Brook Trail (47",
    "Weather": "Calm, Clear, Warm."
  },
  "title": "Zander Scott Trail (48) to Roaring Brook Trail (47",
  "trail_id": "pb_246497"
}