{
  "description": "Designed to handle it all, whether you\u2019re climbing, trekking or training, the Lightwire Tech Tee features a four-way stretch fabric that\u2019s breathable and quick-drying. This ensures that you can move freely, try hard, and keep crushing when you\u2019re going hard. In addition, underarm gussets add extra mobility while reflective logos increase visibility when your adventures push past the daylight hours.",
  "img_hrefs": [
    "https://vpo.ca/images/product/medium/341531.jpg"
  ],
  "name": "Lightwire SS Tech Tee - Womens",
  "price_cents": 7495,
  "specs": [],
  "url": "https://vpo.ca/product/341531/lightwire-ss-tech-tee-womens"
}