{
  "description": "A free-pivoting, alpine touring-style telemark binding, the Voil\u00e9 Switchback allows backcountry telemark skiers to ascend with zero heel resistance thus conserving valuable energy and allowing for easier trail breaking. The Switchback is easily switched from uphill touring to downhill telemark skiing with use of your ski pole. Also, it comes standard equipped with dual height climbing heel elevators for varying ascents.",
  "img_hrefs": [
    "https://vpo.ca/images/product/medium/362506.jpg"
  ],
  "name": "Switchback Binding Standard Rod 27-31",
  "price_cents": 45500,
  "specs": [
    {
      "key": "Materials",
      "value": "Heat treated stainless steel"
    },
    {
      "key": "Boot Size (Mondo Point)",
      "value": "27-31"
    },
    {
      "key": "Boot Sole Length",
      "value": "305-350 mm"
    },
    {
      "key": "Boot Size (US)",
      "value": "9-13"
    },
    {
      "key": "Weight",
      "value": "3 lbs"
    },
    {
      "key": "Riser Height",
      "value": "25 mm"
    },
    {
      "key": "Dual Height Elevators",
      "value": "65mm"
    },
    {
      "key": "Flex/\u200bPerformance",
      "value": "Moderate"
    }
  ],
  "url": "https://vpo.ca/product/362506/switchback-binding-standard-rod-27-31"
}