{
  "description": "<p>Stable trekking and backpacking boots that support feet on rugged terrain. The 1.8mm suede has a waterproof-breathable membrane and a tough rand for abrasion protection. An EVA midsole and anti-torsion shank cushion and support on rough ground, and the stout rubber sole grips when your trek demands some climbing moves.</p><ul><li>Durable suede upper has a stretch fabric collar for a comfortable fit</li><li>GORE-TEX\u00ae waterproof-breathable membrane keeps your feet dry in unfavourable weather</li><li>Polyurethane full rand protects suede from abrasion and adds grip in climbing terrain</li><li>To-the-toe lacing allows a customized fit</li><li>Dual-density EVA midsole has an anti-torsion TPU shank for stability</li><li>Vibram\u00ae LiteBase outsole provides traction in loose terrain</li><li>MegaGrip rubber sticks on friction moves</li></ul>",
  "img_hrefs": [
    "https://cdn11.bigcommerce.com/s-xw5rh7060c/products/48975/images/211746/6016873_DAT00__30449.1700302450.1280.1280.jpg?c=1",
    "https://cdn11.bigcommerce.com/s-xw5rh7060c/products/48975/images/209601/6016873_DAT00_ALT-F__56001.1700302451.1280.1280.jpg?c=1",
    "https://cdn11.bigcommerce.com/s-xw5rh7060c/products/48975/images/209595/6016873_DAT00_ALT-E__29829.1700302450.1280.1280.jpg?c=1",
    "https://cdn11.bigcommerce.com/s-xw5rh7060c/products/48975/images/209588/6016873_DAT00_ALT-D__29534.1700302450.1280.1280.jpg?c=1",
    "https://cdn11.bigcommerce.com/s-xw5rh7060c/products/48975/images/209585/6016873_DAT00_ALT-B__44566.1700302450.1280.1280.jpg?c=1",
    "https://cdn11.bigcommerce.com/s-xw5rh7060c/products/48975/images/209581/6016873_DAT00_ALT-C__87103.1700302450.1280.1280.jpg?c=1",
    "https://cdn11.bigcommerce.com/s-xw5rh7060c/products/48975/images/209578/6016873_DAT00_ALT-A__90239.1700302450.1280.1280.jpg?c=1"
  ],
  "name": "Scarpa Mescalito Trk Gore-Tex Backpacking Boots - Women's",
  "price_cents": 39895,
  "specs": [
    {
      "key": "Weight",
      "value": "1.09kg (38)"
    },
    {
      "key": "Ideal for",
      "value": [
        "Backpacking",
        "Day hiking"
      ]
    },
    {
      "key": "Upper material",
      "value": [
        "Suede"
      ]
    },
    {
      "key": "Closure",
      "value": [
        "Lace-up"
      ]
    },
    {
      "key": "Rand",
      "value": "Full rand"
    },
    {
      "key": "Removable insole",
      "value": "Yes"
    },
    {
      "key": "Waterproof",
      "value": "Yes"
    },
    {
      "key": "Made in",
      "value": "Italy"
    }
  ],
  "url": "https://www.mec.ca/en/product/6016-873/mescalito-trk-gore-tex-backpacking-boots"
}