{
  "description": "<p>The Sole Performance Medium Cork Footbeds are a pair of insoles that are designed to provide comfort, support, and sustainability for your feet. They are made of recycled wine corks that are collected by ReCORK, a natural cork recycling program.</p><ul><li>They have a metatarsal pad that helps relieve pressure and pain from the ball of the foot</li><li>They are heat and wear moldable, which means they can adapt to the shape of your foot over time</li><li>They are also coated with Polygiene, a recycled silver salt treatment that prevents odor-causing bacteria from growing on the insoles</li></ul>",
  "img_hrefs": [
    "https://cdn11.bigcommerce.com/s-xw5rh7060c/products/53305/images/248793/6026512_RED00__64527.1698485890.1280.1280.jpg?c=1"
  ],
  "name": "Sole Performance Medium Cork Footbeds - Unisex",
  "price_cents": 4547,
  "specs": [
    {
      "key": "Ideal for",
      "value": [
        "Travel",
        "Everyday use",
        "Day hiking"
      ]
    },
    {
      "key": "Cleaning",
      "value": "Hand wash"
    },
    {
      "key": "Product sustainability",
      "value": [
        "Recycled content"
      ]
    },
    {
      "key": "Made in",
      "value": "Korea, Republic of"
    }
  ],
  "url": "https://www.mec.ca/en/product/6026-512/performance-medium-cork-footbeds"
}