{
  "center_geohash": "9qmy27b5nt2p",
  "center_lat": 36.2760265,
  "center_lng": -115.65279699999999,
  "description": "",
  "directions": "",
  "geohash": "9qmy2",
  "nearest_peak_geohash": "9qmy2k7sd29w",
  "photos": [],
  "source_url": "https://www.peakbagger.com/climber/ascent.aspx?aid=1495836",
  "stats": {
    "Ascent Type": "Successful Summit Attained",
    "Date": "Sunday, September 20, 2020",
    "Elevation": "9692 ft / 2954 m",
    "Extra Gain": "100 ft / 30 m",
    "Location": "USA-Nevada",
    "Others in Party": "Stacey Kassan",
    "Peak": "Cockscomb Peak",
    "Peakbagger.com": "\n\n\n",
    "Quality": "2 (on a subjective 1-10 scale)",
    "Round-Trip Distance": "5.8 mi / 9.3 km",
    "Route": "via Trail Canyon",
    "Time": "2 Hours\u00a015 Minutes",
    "Total Elevation Gain": "2167 ft / 660 m",
    "Trailhead": "Trail Canyon Trailhead\u00a0\u00a07725 ft / 2354 m"
  },
  "title": "via Trail Canyon",
  "trail_id": "pb_1495836"
}