{
  "center_geohash": "drefx3kw3353",
  "center_lat": 42.634898,
  "center_lng": -73.15172100000001,
  "description": "",
  "directions": "",
  "geohash": "drefx",
  "nearest_peak_geohash": "drefx1fhn96f",
  "photos": [],
  "source_url": "https://www.peakbagger.com/climber/ascent.aspx?aid=574340",
  "stats": {
    "": "",
    "Ascent Type": "Successful Summit Attained",
    "Date": "Sunday, August 23, 2015",
    "Distance": "5.4 mi / 8.7 km",
    "Elevation": "3487 ft / 1062 m",
    "Gain Breakdown": "Net: 2317 ft / 706 m; Extra: 70 ft / 21m",
    "Gain on way in": "2387 ft / 727 m",
    "Location": "USA-Massachusetts",
    "Loss on way in": "70 ft / 21 m",
    "Motorized Transport to Trailhead": "Car",
    "Other People": "Solo Ascent",
    "Peak": "Mount Greylock",
    "Peakbagger.com": "\n\n\n",
    "Route": "Thunderbolt Trail",
    "Start Trailhead": "Thiel Rd\u00a0\u00a01170 ft / 356 m",
    "Total Elevation Gain": "2387 ft / 727 m",
    "Total Elevation Loss": "70 ft / 21 m",
    "Weather": "Drizzle, Cool, Breezy, Low Clouds"
  },
  "title": "Thunderbolt Trail",
  "trail_id": "pb_574340"
}